chainner_ext-0.3.9.dist-info/METADATA
chainner_ext-0.3.9.dist-info/WHEEL
chainner_ext/__init__.py
chainner_ext/__init__.pyi
chainner_ext/py.typed
chainner_ext/chainner_ext.cpython-310-aarch64-linux-gnu.so
chainner_ext-0.3.9.dist-info/RECORD
