Metadata-Version: 2.1
Name: chainner_ext
Version: 0.3.9
Classifier: License :: OSI Approved :: Apache Software License
Classifier: License :: OSI Approved :: MIT License
Classifier: Programming Language :: Rust
Classifier: Programming Language :: Python :: Implementation :: CPython
Classifier: Programming Language :: Python :: Implementation :: PyPy
Classifier: Topic :: Scientific/Engineering :: Image Processing
Requires-Dist: numpy >=1.16.0
Summary: Rust implementation of functionality used in chaiNNer
Author: chaiNNer team
License: MIT OR Apache-2.0
Requires-Python: >=3.7
Project-URL: Homepage, https://github.com/chaiNNer-org/chaiNNer-rs
